{
  "1": {
    "class_type": "CheckpointLoaderSimple",
    "inputs": {
      "ckpt_name": "animagine-xl-4.0-opt.safetensors"
    }
  },
  "2": {
    "class_type": "CLIPTextEncode",
    "inputs": {
      "clip": [
        "1",
        1
      ],
      "text": "masterpiece, best quality, high score, anime style, single simple object, 2D cutout animation prop, centered, isolated on solid hot magenta chroma key background, clean thick outline, flat readable colors, simple shadow, no hand, no person, no text"
    }
  },
  "3": {
    "class_type": "CLIPTextEncode",
    "inputs": {
      "clip": [
        "1",
        1
      ],
      "text": "low quality, worst quality, blurry, realistic photo, 3d render, person, hand, character, text, watermark, logo, background scenery, complex shadows, multiple objects, cropped object"
    }
  },
  "4": {
    "class_type": "EmptyLatentImage",
    "inputs": {
      "width": 768,
      "height": 768,
      "batch_size": 1
    }
  },
  "5": {
    "class_type": "KSampler",
    "inputs": {
      "seed": 2026062501,
      "steps": 24,
      "cfg": 5.5,
      "sampler_name": "euler",
      "scheduler": "normal",
      "denoise": 1,
      "model": [
        "1",
        0
      ],
      "positive": [
        "2",
        0
      ],
      "negative": [
        "3",
        0
      ],
      "latent_image": [
        "4",
        0
      ]
    }
  },
  "6": {
    "class_type": "VAEDecode",
    "inputs": {
      "samples": [
        "5",
        0
      ],
      "vae": [
        "1",
        2
      ]
    }
  },
  "7": {
    "class_type": "SaveImage",
    "inputs": {
      "filename_prefix": "scene_pack_prop",
      "images": [
        "6",
        0
      ]
    }
  }
}
